scdeed/__init__.py
scdeed/common.py
scdeed/scdeed.py
scdeed-0.0.4.dist-info/LICENSE
scdeed-0.0.4.dist-info/METADATA
scdeed-0.0.4.dist-info/WHEEL
scdeed-0.0.4.dist-info/entry_points.txt
scdeed-0.0.4.dist-info/top_level.txt
scdeed-0.0.4.dist-info/RECORD
